LICENSE
README.md
rpapy/__init__.py
rpapy/__main__.py
rpapy/activities.py
rpapy/core/__init__.py
rpapy/core/config.py
rpapy/core/image_mapper.py
rpapy/core/locator.py
rpapy/core/prepare_text.py
rpapy/core/snipps/__init__.py
rpapy/core/snipps/codesnippets.py
rpapy/core/snipps/loads.py
rpapy/core/snipps/snippingtools.py
rpapy/core/snipps/templates.py
rpapy/core/utils/__init__.py
rpapy/core/utils/example/__init__.py
rpapy/core/utils/example/paint_robot.py
rpapy/core/utils/imagens/IMAGEM_NAO_ENCONTRADA.png
rpapy/core/utils/imagens/template_win11_screen_1920x1080.svg
rpapy/core/utils/messages.py
rpapy-1.1.3.dist-info/entry_points.txt
rpapy-1.1.3.dist-info/LICENSE
rpapy-1.1.3.dist-info/METADATA
rpapy-1.1.3.dist-info/WHEEL
rpapy-1.1.3.dist-info/RECORD
