Metadata-Version: 2.1
Name: rpapy
Version: 1.1.3
Summary: RPAPY is a open source easy tool for automating boring stuffs on any screen with robotframework, pyautogui, pywinauto and others.
Home-page: https://github.com/codigo100cera/rpapy
License: MIT
Keywords: rpa,robotframework,automations,tools
Author: Codigo Sem Cera
Author-email: codigo100cera@gmail.com
Requires-Python: >=3.10,<3.13
Classifier: License :: OSI Approved :: MIT License
Classifier: Programming Language :: Python
Classifier: Programming Language :: Python :: 3
Classifier: Programming Language :: Python :: 3.10
Classifier: Programming Language :: Python :: 3.11
Classifier: Programming Language :: Python :: 3.12
Requires-Dist: keyring (>=25.1.0,<26.0.0)
Requires-Dist: mouse (>=0.7.1,<0.8.0)
Requires-Dist: numpy (>=1.26.4,<2.0.0)
Requires-Dist: opencv-python (>=4.9.0.80,<5.0.0.0)
Requires-Dist: pyautogui (>=0.9.54,<0.10.0)
Requires-Dist: pynput (>=1.7.6,<2.0.0)
Requires-Dist: pyperclip (>=1.8.2,<2.0.0)
Requires-Dist: pyside6 (>=6.6.2,<7.0.0)
Requires-Dist: pysimplegui (>=4.0,<5.0)
Requires-Dist: pytesseract (>=0.3.10,<0.4.0)
Requires-Dist: python-dotenv (>=1.0.1,<2.0.0)
Requires-Dist: pywinauto (>=0.6.8,<0.7.0)
Requires-Dist: rpaframework (>=28.3.0,<29.0.0)
Project-URL: Repository, https://github.com/codigo100cera/rpapy
